nearest_neighbor_preprocessor/_init_.py
nearest_neighbor_preprocessor/nn_preprocessor.py
nearest_neighbor_preprocessor-0.1.dist-info/METADATA
nearest_neighbor_preprocessor-0.1.dist-info/WHEEL
nearest_neighbor_preprocessor-0.1.dist-info/top_level.txt
nearest_neighbor_preprocessor-0.1.dist-info/RECORD
