Metadata-Version: 2.1
Name: nearest-neighbor-preprocessor
Version: 0.1
Summary: Simple kNN based preprocessor that converts adverserial images to clean images. This can be used during test time in neural network pipelines.
Home-page: UNKNOWN
Author: Krishnan Pallikkattu Gopakumar
Author-email: UNKNOWN
License: UNKNOWN
Platform: UNKNOWN
Requires-Dist: numpy
Requires-Dist: pynndescent
